{"cameraMode":{"drawMode":0,"name":"Shaded","section":"Shading Mode"},"sceneLighting":false,"audioPlay":false,"sceneViewState":{"m_AlwaysRefresh":false,"showFog":true,"showSkybox":false,"showFlares":true,"showImageEffects":true,"showParticleSystems":true,"showVisualEffectGraphs":true,"m_FxEnabled":true},"in2DMode":false,"pivot":{"x":-19.335689544677736,"y":-14.67817211151123,"z":3.6205177307128908},"rotation":{"x":-0.2533102035522461,"y":0.623481273651123,"z":-0.22407077252864839,"w":-0.7048898935317993},"size":17.86407470703125,"orthographic":false}